socketio_notifier/__init__.py
socketio_notifier/notifier.py
socketio_notfier-1.0.0.dist-info/METADATA
socketio_notfier-1.0.0.dist-info/WHEEL
socketio_notfier-1.0.0.dist-info/RECORD
