Metadata-Version: 2.1
Name: socketio-notfier
Version: 1.0.0
Summary: A library to emit notifications to socketio server
License: GPLv3
Author: IranTheCreator
Author-email: sirzechs.gremory10@gmail.com
Requires-Python: >=3.11,<4.0
Classifier: License :: Other/Proprietary License
Classifier: Programming Language :: Python :: 3
Classifier: Programming Language :: Python :: 3.11
